{
	"info": {
		"_postman_id": "88e9c3c0-557e-4fc8-b2cc-0be76b915a28",
		"name": "MongoDB",
		"schema": "https://schema.getpostman.com/json/collection/v2.1.0/collection.json"
	},
	"item": [
		{
			"name": "findById",
			"request": {
				"method": "GET",
				"header": [],
				"url": {
					"raw": "localhost:8080/person/63b2c50d7fa5b33f78cf99aa",
					"host": [
						"localhost"
					],
					"port": "8080",
					"path": [
						"person",
						"63b2c50d7fa5b33f78cf99aa"
					]
				}
			},
			"response": []
		},
		{
			"name": "addPerson",
			"request": {
				"method": "POST",
				"header": [],
				"body": {
					"mode": "raw",
					"raw": "{\r\n    \"name\": \"Alba\",\r\n    \"age\": 29\r\n}",
					"options": {
						"raw": {
							"language": "json"
						}
					}
				},
				"url": {
					"raw": "localhost:8080/person",
					"host": [
						"localhost"
					],
					"port": "8080",
					"path": [
						"person"
					]
				}
			},
			"response": []
		},
		{
			"name": "deleteById",
			"request": {
				"method": "DELETE",
				"header": [],
				"url": {
					"raw": "localhost:8080/person/63b2c50d7fa5b33f78cf99aa",
					"host": [
						"localhost"
					],
					"port": "8080",
					"path": [
						"person",
						"63b2c50d7fa5b33f78cf99aa"
					]
				}
			},
			"response": []
		},
		{
			"name": "updatePerson",
			"request": {
				"method": "PUT",
				"header": [],
				"body": {
					"mode": "raw",
					"raw": "{\r\n    \"name\": \"Sandra\",\r\n    \"age\": 30\r\n}",
					"options": {
						"raw": {
							"language": "json"
						}
					}
				},
				"url": {
					"raw": "localhost:8080/person/63b2c50d7fa5b33f78cf99aa",
					"host": [
						"localhost"
					],
					"port": "8080",
					"path": [
						"person",
						"63b2c50d7fa5b33f78cf99aa"
					]
				}
			},
			"response": []
		},
		{
			"name": "getPeople",
			"request": {
				"method": "GET",
				"header": [],
				"url": {
					"raw": "localhost:8080/person/people?offset=0&pageSize=10",
					"host": [
						"localhost"
					],
					"port": "8080",
					"path": [
						"person",
						"people"
					],
					"query": [
						{
							"key": "offset",
							"value": "0"
						},
						{
							"key": "pageSize",
							"value": "10"
						}
					]
				}
			},
			"response": []
		}
	]
}